vox/__init__.py
vox/_flags.py
vox/_manager.py
vox/_options.py
vox/_session.py
vox/chain_node/__init__.py
vox/flaggy/__init__.py
vox/linters/__init__.py
vox/linters/base_linter.py
vox/linters/python/__init__.py
vox/linters/python/bandit.py
vox/linters/python/bellybutton.py
vox/linters/python/clonedigger.py
vox/linters/python/coala.py
vox/linters/python/detect_secrets.py
vox/linters/python/dodgy.py
vox/linters/python/flake8.py
vox/linters/python/frosted.py
vox/linters/python/jedi.py
vox/linters/python/mypy.py
vox/linters/python/prospector.py
vox/linters/python/py_find_injection.py
vox/linters/python/pychecker.py
vox/linters/python/pycodestyle.py
vox/linters/python/pydiatra.py
vox/linters/python/pydocstyle.py
vox/linters/python/pyflakes.py
vox/linters/python/pylama.py
vox/linters/python/pylint.py
vox/linters/python/pyre.py
vox/linters/python/pyroma.py
vox/linters/python/python_taint.py
vox/linters/python/pytype.py
vox/linters/python/radon_cc.py
vox/linters/python/radon_hal.py
vox/linters/python/radon_mi.py
vox/linters/python/radon_raw.py
vox/linters/python/twistedchecker.py
vox/linters/python/vulture.py
vox/linty/__init__.py
vox/linty/display.py
vox/linty/from_str.py
vox/linty/helpers.py
vox/linty/to_str.py
vox/mutations/__init__.py
vox/mutations/nosa.py
vox-0.0.1.dist-info/LICENSE
vox-0.0.1.dist-info/METADATA
vox-0.0.1.dist-info/WHEEL
vox-0.0.1.dist-info/top_level.txt
vox-0.0.1.dist-info/RECORD
