Metadata-Version: 2.1
Name: vox
Version: 0.0.1
Summary: Runs linters seperately and outputs them as one.
Home-page: https://peilonrayz.github.io/vox
Author: Peilonrayz
Author-email: peilonrayz@gmail.com
License: MIT
Project-URL: Bug Tracker, https://github.com/Peilonrayz/vox/issues
Project-URL: Documentation, https://peilonrayz.github.io/vox
Project-URL: Source Code, https://github.com/Peilonrayz/vox
Keywords: linter
Platform: UNKNOWN
Classifier: Development Status :: 3 - Alpha
Classifier: Environment :: Console
Classifier: Intended Audience :: Developers
Classifier: License :: OSI Approved :: MIT License
Classifier: Operating System :: OS Independent
Classifier: Programming Language :: Python :: 3.7
Classifier: Programming Language :: Python :: 3.8
Requires-Dist: nox
Requires-Dist: parse
Requires-Dist: typing-extensions
Requires-Dist: mypy-extensions
